paperinquierer/__init__.py
paperinquierer/paperinquirer.py
paperinquirer/__init__.py
paperinquirer/paperinquirer.py
paperinquirer-0.0.9.data/scripts/more_features.py
paperinquirer-0.0.9.data/scripts/simple.py
paperinquirer-0.0.9.dist-info/LICENSE
paperinquirer-0.0.9.dist-info/METADATA
paperinquirer-0.0.9.dist-info/WHEEL
paperinquirer-0.0.9.dist-info/top_level.txt
paperinquirer-0.0.9.dist-info/RECORD
