Metadata-Version: 2.1
Name: paperinquirer
Version: 0.0.9
Summary: A python package to query and search through scientific papers
Home-page: https://github.com/adelhpour/PaperInquirer
Author: Adel Heydarabadipour
Author-email: adelhp@uw.edu
Project-URL: Bug Tracker, https://github.com/adelhpour/PaperInquirer/issues
Classifier: Programming Language :: Python :: 3
Classifier: License :: OSI Approved :: MIT License
Classifier: Operating System :: OS Independent
Requires-Python: >=3.9
License-File: LICENSE
Requires-Dist: llama-index ==0.10.15
